ImgRar/BaseConversion.py
ImgRar/__init__.py
ImgRar/cli.py
Imgrar-1.1.0.dist-info/LICENSE
Imgrar-1.1.0.dist-info/METADATA
Imgrar-1.1.0.dist-info/WHEEL
Imgrar-1.1.0.dist-info/entry_points.txt
Imgrar-1.1.0.dist-info/top_level.txt
Imgrar-1.1.0.dist-info/RECORD
