Metadata-Version: 2.1
Name: Imgrar
Version: 1.1.0
Summary: Small code files to Images and Vice-Versa
Home-page: https://github.com/Otherwa/Imgrar
Author: Atharv Desai
Author-email: atharvdesai2002@gmail.com
Classifier: Programming Language :: Python :: 3
Classifier: License :: OSI Approved :: MIT License
Classifier: Operating System :: OS Independent
Requires-Python: >=3.6
License-File: LICENSE
Requires-Dist: Pillow
